[
    {
        "domainName": "https://www.shephe.com",
        "name": "Kevin's",
        "avatar": "https://cos.lhasa.icu/LinksAvatar/www.shephe.com.png"
    },
    {
        "domainName": "https://1900.live",
        "name": "@1900'Blog",
        "avatar": "https://cos.lhasa.icu/LinksAvatar/1900.live.png"
    },
    {
      "domainName": "https://imiku.me/",
      "name": "Hazymoon",
      "avatar": "https://github.com/Ice-Hazymoon"
    },
    {
      "domainName": "https://www.yyyzyyyz.cn/",
      "name": "Black Flies",
      "avatar": "https://npm.elemecdn.com/imgscdn/img/202111191951780.JPG"
    },
    {
      "domainName": "https://dusays.com/",
      "name": "杜老师说",
      "avatar": "https://cdn.dusays.com/avatar.png/2"
    },
    {
      "domainName": "https://immmmm.com/",
      "name": "木木木木木",
      "avatar": "https://cravatar.cn/avatar/ba83fa02fc4b2ba621514941307e21be?d=identicon"
    },
    {
      "domainName": "https://www.shephe.com/",
      "name": "牧羊人",
      "avatar": "https://dn-qiniu-avatar.qbox.me/avatar/cbbe656c7bb46772f589c9b18a7c747e?s=100&d=identicon&r=g"
    },
    {
      "domainName": "https://www.sulvblog.cn/",
      "name": "Sulv’s Blog",
      "avatar": "https://www.sulvblog.cn/img/Q.gif"
    },
    {
      "domainName": "https://eallion.com/",
      "name": "大大的小蜗牛",
      "avatar": "https://secure.gravatar.com/avatar/171e4c30959e8c077a6c58b958624b31"
    },
    {
      "domainName": "https://guanqr.com/",
      "name": "荷戟独彷徨",
      "avatar": "https://cdn.jsdelivr.net/gh/guanqr/blog/static/icons/android-chrome-512x512.png"
    },
    {
      "domainName": "https://thiscute.world/",
      "name": "This Cute World",
      "avatar": "https://thiscute.world/avatar/myself.webp"
    },
    {
      "domainName": "https://www.shifeiti.com",
      "name": "是非题",
      "avatar": "https://other.shifeiti.com/logo/logo.png"
    },
    {
      "domainName": "https://tin6.com/",
      "name": "消夏绿",
      "avatar": "https://tin6.com/media/aboutme.jpg"
    },
    {
      "domainName": "https://frytea.com/",
      "name": "Frytea",
      "avatar": "https://avatars.githubusercontent.com/u/31945314?v=4"
    },
    {
      "domainName": "https://inkss.cn",
      "name": "枋柚梓的猫会发光",
      "avatar": "https://o.static.szyink.com/common/static/hexo/inkss.jpeg"
    },
    {
      "domainName": "https://blog.sakurasep.site/",
      "name": "上杉九月的博客",
      "avatar": "https://xingqiu-tuchuang-1256524210.cos.ap-shanghai.myqcloud.com/5199/touxiang.jpg"
    },
    {
      "domainName": "https://sxxkearth.github.io/",
      "name": "嗜血星空",
      "avatar": "https://sxxkearth.github.io/img/avatar.svg"
    },
    {
      "domainName": "https://uyoahz.cn/",
      "name": "UyoAhz",
      "avatar": "https://q1.qlogo.cn/g?b=qq&nk=2496091142&s=640"
    },
    {
      "domainName": "https://waynerv.com/",
      "name": "Shall We Code",
      "avatar": "https://avatars.githubusercontent.com/u/39515546?v=4"
    },
    {
      "domainName": "https://www.sulvblog.cn",
      "name": "Sulv’s Blog",
      "avatar": "https://www.sulvblog.cn/img/Q.gif"
    },
    {
      "domainName": "https://lisenhui.cn",
      "name": "凡梦星尘空间站",
      "avatar": "https://lisenhui.cn/imgs/avatar.png"
    },
    {
      "domainName": "https://www.thyuu.com",
      "name": "风记星辰",
      "avatar": "https://std.thyuu.com/logo.webp"
    },
    {
      "domainName": "https://blog.didctf.com/",
      "name": "DIDCTF-Blog",
      "avatar": "https://s-cd-3454-didctf.oss.dogecdn.com/logo/didctf.jpg"
    },
    {
      "domainName": "https://www.jdeal.cn",
      "name": "Jdeal",
      "avatar": "https://qn.jdeal.cn/jh.jpg"
    },
    {
      "domainName": "https://blog.starysky.top",
      "name": "USTC-茶糜花开",
      "avatar": "https://blog.starysky.top/img/blog_avatar.jpg"
    },
    {
      "domainName": "https://bio-w.cn/",
      "name": "西瓜撞地球",
      "avatar": "https://bu.dusays.com/2022/10/17/634d313602a1e.png"
    },
    {
      "domainName": "https://hutusi.com/",
      "name": "胡涂说",
      "avatar": "https://www.seersu.me/favicon/avatar.jpg"
    },
    {
      "domainName": "https://blognas.hwb0307.com",
      "name": "浮云翩迁之间",
      "avatar": "https://blognas.hwb0307.com/logo.jpg"
    },
    {
      "domainName": "https://www.liveout.cn/",
      "name": "Echo’s blog",
      "avatar": "https://yy.liveout.cn/photo/photo2.jpg"
    },
    {
      "domainName": "https://easyf12.top/",
      "name": "一蓑烟雨的博客",
      "avatar": "https://img.easyf12.top/images/2022/10/15/634a8b4186889.webp"
    },
    {
      "domainName": "https://shixiaocaia.fun",
      "name": "Shixiaocaia",
      "avatar": "https://bu.dusays.com/2022/12/25/63a806f74cf5e.jpg"
    },
    {
      "domainName": "https://blog.el9.cn",
      "name": "小卢",
      "avatar": "https://api.el9.cn/img/blogtx.php"
    },
    {
      "domainName": "https://vlieo.com/",
      "name": "记忆一隅",
      "avatar": "https://vlieo.com/images/avatar.png?v=1674992080987"
    },
    {
      "domainName": "https://blog.leonus.cn",
      "name": "Leonus",
      "avatar": "https://q1.qlogo.cn/g?b=qq&nk=990320751&s=5"
    },
    {
      "domainName": "https://jingxin18.cn",
      "name": "二猫 blog",
      "avatar": "https://jingxin18.cn/wp-content/uploads/2023/02/1677583088-1.webp"
    },
    {
      "domainName": "https://blog.cuger.cn",
      "name": "Dorad",
      "avatar": "https://blog.cuger.cn/images/avatar.png"
    },
    {
      "domainName": "https://wenderfeng.top/",
      "name": "wenderfeng",
      "avatar": "https://wenderfeng.top/favicon.ico"
    },
    {
      "domainName": "https://nanwish.love",
      "name": "墨点白",
      "avatar": "https://nanormal.oss-cn-hangzhou.aliyuncs.com/blogFile/49705984.jpg"
    },
    {
      "domainName": "https://muxer.cn/",
      "name": "不亦乐乎",
      "avatar": "https://cravatar.cn/avatar/d9cc49ea0301640d7a19b6a1e77012dd?s=110&d=mm&r=g"
    },
    {
      "domainName": "https://lhasa.icu/",
      "name": "游钓四方的博客",
      "avatar": "https://cos.lhasa.icu/StylePictures/my-photo.jpg_640"
    },
    {
      "domainName": "https://hongtaoh.com/cn/blog/",
      "name": "hongtaoh",
      "avatar": "https://hongtaoh.com/media/me_cali_2023_summer.png"
    },
    {
        "domainName": "https://tianheg.co",
        "name": "yijiadabei",
        "avatar": "https://cravatar.cn/avatar/d9cc49ea0301640d7a19b6a1e77012dd?s=110&d=mm&r=g"
    }
  ]
  
